{"General": {"N_SPEAKERS": 5, "SAMPLE_RATE": 10000, "NFFT": 512, "SIGNAL_DURATION_IN_SECONDS": 10.0}, "Frames": {"SAMPLE_RATE": 10000, "NFFT": 512, "VAD_TRESHOLD": 0.02, "PRE_EMPHASIS_COEF": 0.99, "FRAME_IN_SECS": 0.02, "OVERLAP_PCT": 0.2, "WINDOW": "hanning", "OVERLAP_IN_SECS": 0.004}, "MFB": {"NFFT": 512, "SAMPLE_RATE": 10000, "N_FILT": 40, "N_CEPS": 22, "CEP_LIFTER": 22}, "MFCC": {"NFFT": 512, "SAMPLE_RATE": 10000, "N_FILT": 40, "N_CEPS": 22, "CEP_LIFTER": 22}, "LPC": {"P": 12}, "PLP": {"P": 12}, "Model attr": {"VQ": {"N_CODEWORDS": 40, "EPOCHS": 50}, "GMM": {"N_MIXTURES": 350, "EPOCHS": 5000}, "SVM": {"EPOCHS": 5000}}, "Execution times": {"File reading": 5.32, "Pre-processing": 0.95, "MFB": 35.7, "MFCC": 44.73, "LPC": 106.96, "PLP": 3.54, "VQ MFB": 541.97, "GMM MFB": 27.33, "SVM MFB": 225.47, "VQ MFCC": 886.62, "GMM MFCC": 94.84, "SVM MFCC": 294.05, "VQ LPC": 185.71, "GMM LPC": 1.29, "SVM LPC": 3.78, "VQ PLP": 23.35, "GMM PLP": 1.55, "SVM PLP": 3.78}, "Results": {"Model": "VQ", "Features": "LPC", "Confusion matrix": [["5688", "5688"], ["5688", "5688"], ["5688", "5688"], ["5688", "5688"], ["5703", "5703"], ["5703", "5703"], ["5703", "5703"], ["5703", "5703"], ["5703", "5703"], ["5703", "5703"], ["3857", "3857"], ["3857", "3857"], ["3857", "3857"], ["3857", "3857"], ["3857", "3857"], ["3857", "3857"], ["8108", "8108"], ["8108", "8108"], ["8108", "8108"], ["8108", "8108"], ["8108", "8108"], ["3436", "3436"], ["3436", "3436"], ["3436", "3436"], ["3436", "3436"], ["3436", "3436"], ["3436", "3436"]]}}